simultaneous/QUICK_TEST.py
simultaneous/__init__.py
simultaneous/browsers.py
simultaneous/code_interpreters.py
simultaneous/containers.py
simultaneous/agent/__init__.py
simultaneous/agent/local.py
simultaneous/agent/pack.py
simultaneous/agent/spec.py
simultaneous/agentic/__init__.py
simultaneous/agentic/base.py
simultaneous/agentic/e2b.py
simultaneous/agentic/utils.py
simultaneous/client/__init__.py
simultaneous/client/base.py
simultaneous/client/browser.py
simultaneous/client/code_interpreter.py
simultaneous/client/container.py
simultaneous/client/llms.py
simultaneous/client/logs.py
simultaneous/client/runs.py
simultaneous/client/sim_client.py
simultaneous/client/workflows.py
simultaneous/providers/__init__.py
simultaneous/providers/base.py
simultaneous/providers/browserbase.py
simultaneous/providers/e2b.py
simultaneous/providers/router.py
simultaneous/runtime/__init__.py
simultaneous/runtime/base.py
simultaneous/runtime/browser.py
simultaneous/runtime/desktop.py
simultaneous/runtime/sandbox.py
simultaneous/utils/__init__.py
simultaneous/utils/env.py
simultaneous/utils/ids.py
simultaneous/utils/json.py
simultaneous/utils/sse.py
simultaneous-0.1.1.dist-info/licenses/LICENSE
simultaneous-0.1.1.dist-info/METADATA
simultaneous-0.1.1.dist-info/WHEEL
simultaneous-0.1.1.dist-info/top_level.txt
simultaneous-0.1.1.dist-info/RECORD
