Metadata-Version: 2.4
Name: simultaneous
Version: 0.1.1
Summary: SDK for Simultaneous - run agents across multiple providers
Author: Simultaneous Team
License-Expression: MIT
Keywords: agents,automation,browser,stagehand,browserbase
Classifier: Development Status :: 3 - Alpha
Classifier: Intended Audience :: Developers
Classifier: Programming Language :: Python :: 3
Classifier: Programming Language :: Python :: 3.11
Classifier: Programming Language :: Python :: 3.12
Requires-Python: >=3.11
License-File: LICENSE
Requires-Dist: httpx>=0.27.0
Requires-Dist: pydantic>=2.0.0
Requires-Dist: python-dotenv>=1.0.0
Requires-Dist: anyio>=4.0.0
Requires-Dist: ulid-py>=1.1.0
Requires-Dist: rich>=13.0.0
Requires-Dist: pyyaml>=6.0.0
Requires-Dist: stagehand>=0.5.0
Requires-Dist: browserbase>=1.0.0
Requires-Dist: litellm>=1.0.0
Provides-Extra: dev
Requires-Dist: pytest>=7.4.0; extra == "dev"
Requires-Dist: pytest-asyncio>=0.21.0; extra == "dev"
Requires-Dist: mypy>=1.5.0; extra == "dev"
Requires-Dist: ruff>=0.1.0; extra == "dev"
Requires-Dist: types-python-dotenv>=1.0.0; extra == "dev"
Dynamic: license-file
